aleph/__init__.py
aleph/cli.py
aleph/config.py
aleph/core.py
aleph/types.py
aleph/cache/__init__.py
aleph/cache/base.py
aleph/cache/memory.py
aleph/mcp/__init__.py
aleph/mcp/local_server.py
aleph/mcp/server.py
aleph/prompts/__init__.py
aleph/prompts/system.py
aleph/providers/__init__.py
aleph/providers/anthropic.py
aleph/providers/base.py
aleph/providers/openai.py
aleph/providers/registry.py
aleph/repl/__init__.py
aleph/repl/helpers.py
aleph/repl/sandbox.py
aleph/utils/__init__.py
aleph/utils/logging.py
aleph/utils/tokens.py
iflow_mcp_aleph_rlm-0.2.0.dist-info/METADATA
iflow_mcp_aleph_rlm-0.2.0.dist-info/WHEEL
iflow_mcp_aleph_rlm-0.2.0.dist-info/entry_points.txt
iflow_mcp_aleph_rlm-0.2.0.dist-info/licenses/LICENSE
iflow_mcp_aleph_rlm-0.2.0.dist-info/RECORD
