Metadata-Version: 2.4
Name: iflow-mcp_aleph-rlm
Version: 0.2.0
Summary: MCP server for recursive LLM reasoning—load context, iterate with search/code/think tools, converge on answers
Project-URL: Homepage, https://github.com/Hmbown/Aleph-RLM
Author: Aleph Contributors
License: MIT License
License-File: LICENSE
Requires-Python: >=3.10
Requires-Dist: httpx>=0.27.0
Provides-Extra: dev
Requires-Dist: mypy>=1.8.0; extra == 'dev'
Requires-Dist: pytest-asyncio>=0.23.0; extra == 'dev'
Requires-Dist: pytest>=8.0.0; extra == 'dev'
Provides-Extra: mcp
Requires-Dist: mcp>=1.0.0; extra == 'mcp'
Provides-Extra: openai-tokens
Requires-Dist: tiktoken>=0.7.0; extra == 'openai-tokens'
Provides-Extra: rich
Requires-Dist: rich>=13.0.0; extra == 'rich'
Provides-Extra: yaml
Requires-Dist: pyyaml>=6.0; extra == 'yaml'
